featureordering-0.1.4.dist-info/licenses/LICENSE
tabseq_feature_ordering/__init__.py
tabseq_feature_ordering/feature_ordering.py
featureordering-0.1.4.dist-info/METADATA
featureordering-0.1.4.dist-info/WHEEL
featureordering-0.1.4.dist-info/top_level.txt
featureordering-0.1.4.dist-info/RECORD
