Metadata-Version: 2.4
Name: FeatureOrdering
Version: 0.1.4
Summary: Feature Ordering Module from TabSeq (ICPR 2024)
Home-page: https://github.com/zadid6pretam/TabSeq
Author: Zadid Habib
Author-email: ah00069@mix.wvu.edu
Classifier: Programming Language :: Python :: 3
Classifier: License :: OSI Approved :: MIT License
Classifier: Operating System :: OS Independent
Requires-Python: >=3.8
License-File: LICENSE
Requires-Dist: numpy<1.25,>=1.22
Requires-Dist: pandas<2.2,>=2.0.0
Requires-Dist: scikit-learn<1.4,>=1.2
Requires-Dist: networkx<3.2,>=3.0
Dynamic: author
Dynamic: author-email
Dynamic: classifier
Dynamic: description
Dynamic: description-content-type
Dynamic: home-page
Dynamic: license-file
Dynamic: requires-dist
Dynamic: requires-python
Dynamic: summary
